{
  "2026/2/7～8：山口":{
    "days":[
      [
        {
        "departure":"06:30",
        "arrival":"09:00",
        "distance":"265.0km",
        "city":"廿日市市",
        "title":"廿日市市中央市民センター",
        "address":"広島県廿日市市天神11-29",
        "manhole_url":"https://www.gk-p.jp/mhcard/?pref=34",
        "url":"https://www.city.hatsukaichi.hiroshima.jp/soshiki/120/33207.html"
        },
        {
        "departure":"09:10",
        "arrival":"09:50",
        "distance":"26.8km",
        "city":"和木町",
        "title":"和木町蜂ヶ峯総合公園 管理棟",
        "address":"山口県玖珂郡和木町大字瀬田紺屋作260-1",
        "manhole_url":"https://www.gk-p.jp/mhcard/?pref=35",
        "url":"https://www.town.waki.lg.jp/soshiki/3/186.html"
        },
        {
        "departure":"10:00",
        "arrival":"10:20",
        "distance":"10.7km",
        "city":"岩国市②",
        "title":"岩国市観光交流所本家 松がね",
        "address":"山口県岩国市岩国1丁目7-3",
        "manhole_url":"https://www.gk-p.jp/mhcard/?pref=35",
        "url":"https://www.city.iwakuni.lg.jp/soshiki/26/98824.html"
        },
        {
        "departure":"10:30",
        "arrival":"10:50",
        "distance":"-",
        "city":"★観光",
        "title":"岩国城・錦帯橋",
        "address":"山口県岩国市横山３丁目",
        "manhole_url":"-",
        "url":"https://yamaguchi-tourism.jp/spot/detail_11341.html"
        },
        {
        "departure":"10:50",
        "arrival":"11:10",
        "distance":"6.6km",
        "city":"★昼食",
        "title":"寿栄広食堂",
        "address":"山口県岩国市麻里布町1-2-3",
        "manhole_url":"-",
        "url":"https://tabelog.com/yamaguchi/A3506/A350601/35000016/"
        },
        {
        "departure":"12:10",
        "arrival":"12:20",
        "distance":"1.4km",
        "city":"岩国市①",
        "title":"岩国市英語交流センター「PLAT ABC」",
        "address":"山口県岩国市元町⼀丁⽬1番1号 レジデンス岩国駅東1階",
        "manhole_url":"https://www.gk-p.jp/mhcard/?pref=35",
        "url":"https://www.city.iwakuni.lg.jp/soshiki/26/98824.html"
        },
        {
        "departure":"12:30",
        "arrival":"13:10",
        "distance":"31.5km",
        "city":"柳井市",
        "title":"柳井市観光協会",
        "address":"山口県柳井市柳井3714-1",
        "manhole_url":"https://www.gk-p.jp/mhcard/?pref=35",
        "url":"https://www.city-yanai.jp/soshiki/72/gesuika-do.html"
        },
        {
        "departure":"13:20",
        "arrival":"14:00",
        "distance":"28.7km",
        "city":"下松市①②",
        "title":"下松市観光案内所",
        "address":"山口県下松市西豊井1247(下松駅南口)",
        "manhole_url":"https://www.gk-p.jp/mhcard/?pref=35",
        "url":"https://www.city.kudamatsu.lg.jp/sui-gesui/kurashi/jougesuidou/gesuidou/manhole-card.html"
        },
        {
        "departure":"14:10",
        "arrival":"14:20",
        "distance":"8.2km",
        "city":"周南市",
        "title":"周南市観光案内所まちのポート",
        "address":"山口県周南市みなみ銀座1-26 TOKUYAMA DECK D1 1階",
        "manhole_url":"https://www.gk-p.jp/mhcard/?pref=35",
        "url":"https://kanko-shunan.com/"
        },
        {
        "departure":"14:30",
        "arrival":"15:10",
        "distance":"29.9km",
        "city":"防府市",
        "title":"防府市地域交流センター（アスピラート） 1階事務室",
        "address":"山口県防府市戎町1-1-28",
        "manhole_url":"https://www.gk-p.jp/mhcard/?pref=35",
        "url":"https://www.city.hofu.yamaguchi.jp/site/jougesui/manhole-cardhaihu.html"
        },
        {
        "departure":"15:20",
        "arrival":"15:50",
        "distance":"29.9km",
        "city":"山口市④",
        "title":"阿知須いぐらの館",
        "address":"山口県山口市阿知須3425",
        "manhole_url":"https://www.gk-p.jp/mhcard/?pref=35",
        "url":"https://water-city-yamaguchi.com/for-kids/page_1089/"
        },
        {
        "departure":"16:00",
        "arrival":"16:10",
        "distance":"40.5km",
        "city":"宇部市①",
        "title":"ときわ湖水ホール",
        "address":"山口県宇部市大字沖宇部254",
        "manhole_url":"https://www.gk-p.jp/mhcard/?pref=35",
        "url":"https://www.city.ube.yamaguchi.jp/kurashi/gasgesui/1015032/1015277/1015109.html"
        },
        {
        "departure":"16:20",
        "arrival":"16:30",
        "distance":"5.4km",
        "city":"宇部市②",
        "title":"宇部市新川ふれあいセンター",
        "address":"山口県宇部市朝日町8-20",
        "manhole_url":"https://www.gk-p.jp/mhcard/?pref=35",
        "url":"https://www.city.ube.yamaguchi.jp/kurashi/gasgesui/1015032/1015277/1015113.html"
        },
        {
        "departure":"16:40",
        "arrival":"17:00",
        "distance":"8.9km",
        "city":"山陽小野田市①",
        "title":"歴史民俗資料館",
        "address":"山口県山陽小野田市栄町9-21",
        "manhole_url":"https://www.gk-p.jp/mhcard/?pref=35",
        "url":"https://www.city.sanyo-onoda.lg.jp/soshiki/27/manholecard.html"
        },
        {
        "departure":"17:10",
        "arrival":"17:20",
        "distance":"1.4km",
        "city":"山陽小野田市②",
        "title":"おのサンサッカーパーク（山陽小野田市立サッカー交流公園）",
        "address":"山口県山陽小野田市大字小野田7525-17",
        "manhole_url":"https://www.gk-p.jp/mhcard/?pref=35",
        "url":"https://www.city.sanyo-onoda.lg.jp/soshiki/27/renofa-manholecard.html"
        },
        {
        "departure":"17:30",
        "arrival":"18:10",
        "distance":"45.2km",
        "city":"ホテル",
        "title":"スカイハートホテル下関",
        "address":"山口県下関市岬之町6-7",
        "manhole_url":"-",
        "url":"https://www.sky-hotel.jp/shimonoseki/"
        },
        {
        "departure":"18:40",
        "arrival":"19:00",
        "distance":"1.2km",
        "city":"★晩飯",
        "title":"大衆酒場 三枡",
        "address":"山口県下関市竹崎町2-13-11 三枡ビル",
        "manhole_url":"-",
        "url":"https://tabelog.com/yamaguchi/A3502/A350201/35002350/"
        }
      ],
      [
        {
        "departure":"08:40",
        "arrival":"09:00",
        "distance":"7.3km",
        "city":"下関市②",
        "title":"長府庭園",
        "address":"山口県下関市長府黒門東町8番11号",
        "manhole_url":"https://www.gk-p.jp/mhcard/?pref=35",
        "url":"https://www.city.shimonoseki.lg.jp/site/water/5654.html"
        },
        {
        "departure":"09:00",
        "arrival":"09:10",
        "distance":"0.7km",
        "city":"下関市①",
        "title":"長府観光会館",
        "address":"山口県下関市長府侍町二丁目1-15",
        "manhole_url":"https://www.gk-p.jp/mhcard/?pref=35",
        "url":"https://www.city.shimonoseki.lg.jp/site/water/5647.html"
        },
        {
        "departure":"09:20",
        "arrival":"10:20",
        "distance":"51.5km",
        "city":"★観光",
        "title":"角島大橋",
        "address":"山口県下関市豊北町神田～角島",
        "manhole_url":"-",
        "url":"https://yamaguchi-tourism.jp/spot/detail_11030.html"
        },
        {
        "departure":"10:40",
        "arrival":"11:40",
        "distance":"54.1km",
        "city":"萩市",
        "title":"萩・明倫学舎",
        "address":"山口県萩市大字江向602番地",
        "manhole_url":"https://www.gk-p.jp/mhcard/?pref=35",
        "url":"https://www.city.hagi.lg.jp/soshiki/105/h29713.html"
        },
        {
        "departure":"11:50",
        "arrival":"12:30",
        "distance":"34.7km",
        "city":"★昼食",
        "title":"やまむら",
        "address":"山口県美祢市美東町真名2256",
        "manhole_url":"-",
        "url":"https://tabelog.com/yamaguchi/A3504/A350402/35000142/"
        },
        {
        "departure":"13:30",
        "arrival":"13:50",
        "distance":"11.2km",
        "city":"美祢市",
        "title":"秋芳洞案内所",
        "address":"山口県美祢市秋芳町秋吉3449番地1",
        "manhole_url":"https://www.gk-p.jp/mhcard/?pref=35",
        "url":"https://karusuto.com/"
        },
        {
        "departure":"14:00",
        "arrival":"15:00",
        "distance":"-",
        "city":"★観光",
        "title":"秋芳洞",
        "address":"山口県美祢市秋芳町秋吉3449番地1",
        "manhole_url":"-",
        "url":"https://karusuto.com/"
        },
        {
        "departure":"15:00",
        "arrival":"15:30",
        "distance":"23.1km",
        "city":"山口市②",
        "title":"新山口駅観光交流センター",
        "address":"山口県山口市小郡令和1-2-6",
        "manhole_url":"https://www.gk-p.jp/mhcard/?pref=35",
        "url":"https://water-city-yamaguchi.com/for-kids/page_1089/"
        },
        {
        "departure":"15:40",
        "arrival":"16:00",
        "distance":"10.4km",
        "city":"山口市③",
        "title":"湯田温泉観光案内所",
        "address":"山口県山口市湯田温泉2-1-23",
        "manhole_url":"https://www.gk-p.jp/mhcard/?pref=35",
        "url":"https://water-city-yamaguchi.com/for-kids/page_1089/"
        },
        {
        "departure":"16:10",
        "arrival":"16:20",
        "distance":"3.0km",
        "city":"山口市①",
        "title":"山口観光案内所",
        "address":"山口県山口市惣太夫町2-1（山口駅1階）",
        "manhole_url":"https://www.gk-p.jp/mhcard/?pref=35",
        "url":"https://water-city-yamaguchi.com/for-kids/page_1089/"
        },
        {
        "departure":"16:30",
        "arrival":"22:00",
        "distance":"367.0km",
        "city":"-",
        "title":"西川家",
        "address":"兵庫県姫路市飾磨区今在家7-62",
        "manhole_url":"-",
        "url":""
        }
      ]
    ]
  },
    "2025/12/6：岐阜":{
    "days":[
      [
        {
        "departure":"05:00",
        "arrival":"08:00",
        "distance":"243.0km",
        "city":"郡上市④",
        "title":"道の駅 美並物産館",
        "address":"岐阜県郡上市美並町上田2605",
        "manhole_url":"https://www.gk-p.jp/mhcard/?pref=21",
        "url":"https://www.city.gujo.gifu.jp/admin/info/post-1158.html"
        },
        {
        "departure":"08:10",
        "arrival":"08:40",
        "distance":"20.3km",
        "city":"郡上市③",
        "title":"郡上八幡旧庁舎記念館",
        "address":"岐阜県郡上市八幡町島谷520-1",
        "manhole_url":"https://www.gk-p.jp/mhcard/?pref=21",
        "url":"https://www.city.gujo.gifu.jp/admin/info/post-1158.html"
        },
        {
        "departure":"08:50",
        "arrival":"09:00",
        "distance":"1.6km",
        "city":"郡上市①",
        "title":"郡上八幡駅 観光案内所",
        "address":"岐阜県郡上市八幡町城南188-54",
        "manhole_url":"https://www.gk-p.jp/mhcard/?pref=21",
        "url":"https://www.city.gujo.gifu.jp/admin/info/post-1158.html"
        },
        {
        "departure":"09:10",
        "arrival":"09:20",
        "distance":"10.7km",
        "city":"郡上市②",
        "title":"道の駅 古今伝授の里やまと",
        "address":"岐阜県郡上市大和町剣164",
        "manhole_url":"https://www.gk-p.jp/mhcard/?pref=21",
        "url":"https://www.city.gujo.gifu.jp/admin/info/post-1158.html"
        },
        {
        "departure":"09:30",
        "arrival":"10:00",
        "distance":"35.0km",
        "city":"高山市④",
        "title":"高山市荘川支所",
        "address":"岐阜県高山市荘川町新渕430-1",
        "manhole_url":"https://www.gk-p.jp/mhcard/?pref=21",
        "url":"https://www.city.takayama.lg.jp/kurashi/1000022/1000122/1001131/1022809.html"
        },
        {
        "departure":"10:10",
        "arrival":"10:40",
        "distance":"34.2km",
        "city":"高山市⑨",
        "title":"高山市清見支所 当直室窓口",
        "address":"岐阜県高山市清見町三日町305",
        "manhole_url":"https://www.gk-p.jp/mhcard/?pref=21",
        "url":"https://www.city.takayama.lg.jp/kurashi/1000022/1000122/1001131/1022809.html"
        },
        {
        "departure":"10:50",
        "arrival":"11:10",
        "distance":"7.7km",
        "city":"高山市①",
        "title":"高山市役所 当直室",
        "address":"岐阜県高山市花岡町2-18",
        "manhole_url":"https://www.gk-p.jp/mhcard/?pref=21",
        "url":"https://www.city.takayama.lg.jp/kurashi/1000022/1000122/1001131/1022809.html"
        },
        {
        "departure":"11:20",
        "arrival":"11:30",
        "distance":"1.1km",
        "city":"★昼食",
        "title":"まさごそば",
        "address":"岐阜県高山市有楽町31-3",
        "manhole_url":"-",
        "url":"https://tabelog.com/gifu/A2104/A210401/21000021/"
        },
        {
        "departure":"12:30",
        "arrival":"12:40",
        "distance":"8.5km",
        "city":"高山市⑤",
        "title":"高山市一之宮支所",
        "address":"岐阜県高山市一之宮町3100",
        "manhole_url":"https://www.gk-p.jp/mhcard/?pref=21",
        "url":"https://www.city.takayama.lg.jp/kurashi/1000022/1000122/1001131/1022809.html"
        },
        {
        "departure":"12:50",
        "arrival":"13:00",
        "distance":"6.5km",
        "city":"高山市⑥",
        "title":"高山市久々野支所 当直室窓口",
        "address":"岐阜県高山市久々野町無数河580-1",
        "manhole_url":"https://www.gk-p.jp/mhcard/?pref=21",
        "url":"https://www.city.takayama.lg.jp/kurashi/1000022/1000122/1001131/1022809.html"
        },
        {
        "departure":"13:10",
        "arrival":"13:30",
        "distance":"10.3km",
        "city":"高山市⑦",
        "title":"道の駅 ひだ朝日村",
        "address":"岐阜県高山市朝日町万石150",
        "manhole_url":"https://www.gk-p.jp/mhcard/?pref=21",
        "url":"https://www.city.takayama.lg.jp/kurashi/1000022/1000122/1001131/1022809.html"
        },
        {
        "departure":"13:40",
        "arrival":"14:00",
        "distance":"17.1km",
        "city":"高山市⑧",
        "title":"高山市丹生川支所",
        "address":"岐阜県高山市丹生川町坊方2000",
        "manhole_url":"https://www.gk-p.jp/mhcard/?pref=21",
        "url":"https://www.city.takayama.lg.jp/kurashi/1000022/1000122/1001131/1022809.html"
        },
        {
        "departure":"14:10",
        "arrival":"14:30",
        "distance":"12.2km",
        "city":"高山市③",
        "title":"高山市国府支所",
        "address":"岐阜県高山市国府町広瀬町880-1",
        "manhole_url":"https://www.gk-p.jp/mhcard/?pref=21",
        "url":"https://www.city.takayama.lg.jp/kurashi/1000022/1000122/1001131/1022809.html"
        },
        {
        "departure":"14:40",
        "arrival":"14:50",
        "distance":"4.1km",
        "city":"飛騨市①",
        "title":"飛騨古川まちなか観光案内所",
        "address":"岐阜県飛騨市古川町壱之町8-3",
        "manhole_url":"https://www.gk-p.jp/mhcard/?pref=21",
        "url":"https://www.city.hida.gifu.jp/soshiki/15/manhorucard.html"
        },
        {
        "departure":"15:00",
        "arrival":"16:00",
        "distance":"50.8km",
        "city":"高山市②",
        "title":"奥飛騨温泉郷観光案内所",
        "address":"岐阜県高山市奥飛騨温泉郷神坂710-9",
        "manhole_url":"https://www.gk-p.jp/mhcard/?pref=21",
        "url":"https://www.city.takayama.lg.jp/kurashi/1000022/1000122/1001131/1022809.html"
        },
        {
        "departure":"16:10",
        "arrival":"16:50",
        "distance":"31.5km",
        "city":"飛騨市②",
        "title":"道の駅スカイドーム神岡",
        "address":"",
        "manhole_url":"https://www.gk-p.jp/mhcard/?pref=21",
        "url":"https://www.city.hida.gifu.jp/soshiki/15/manhorucard.html"
        },
        {
        "departure":"17:00",
        "arrival":"17:50",
        "distance":"38.2km",
        "city":"★夕食",
        "title":"味の与平",
        "address":"岐阜県高山市上三之町105",
        "manhole_url":"-",
        "url":"https://tabelog.com/gifu/A2104/A210401/21009589/"
        },
        {
        "departure":"19:00",
        "arrival":"23:00",
        "distance":"337.0km",
        "city":"-",
        "title":"西川家",
        "address":"兵庫県神戸市長田区東尻池町2-4-16",
        "manhole_url":"-",
        "url":""
        }
      ]
    ]
  }
}
